tgbotgen/__init__.py
tgbotgen/__main__.py
tgbotgen/scaffold.py
tgbotgen-0.2.1.dist-info/licenses/LICENSE.txt
tgbotgen-0.2.1.dist-info/METADATA
tgbotgen-0.2.1.dist-info/WHEEL
tgbotgen-0.2.1.dist-info/entry_points.txt
tgbotgen-0.2.1.dist-info/top_level.txt
tgbotgen-0.2.1.dist-info/RECORD
