Metadata-Version: 2.4
Name: tgbotgen
Version: 0.2.1
Summary: Генератор структуры проекта для Telegram-бота
Author: Александр Аваков
Requires-Python: >=3.8
License-File: LICENSE.txt
Requires-Dist: aiogram==3.3.0
Requires-Dist: SQLAlchemy==2.0.40
Requires-Dist: python-dotenv==0.9.0
Requires-Dist: APScheduler==3.11.0
Requires-Dist: aiosqlite==0.21.0
Requires-Dist: gspread==6.2.1
Requires-Dist: oauth2client==4.1.3
Requires-Dist: google-api-python-client~=2.179.0
Dynamic: author
Dynamic: license-file
Dynamic: requires-dist
Dynamic: requires-python
Dynamic: summary
